post_generation/__init__.py
post_generation/__main__.py
post_generation/hierarchy_to_countries.py
post_generation/inject_promo_ids.py
post_generation/localads_mwm_to_csv.py
omim_post_generation-10.3.0rc2.dist-info/METADATA
omim_post_generation-10.3.0rc2.dist-info/WHEEL
omim_post_generation-10.3.0rc2.dist-info/top_level.txt
omim_post_generation-10.3.0rc2.dist-info/RECORD
