Metadata-Version: 2.1
Name: omim-post-generation
Version: 10.3.0rc2
Summary: This package is a library for post-processing the generated maps.
Home-page: https://github.com/mapsme
Author: My.com B.V. (Mail.Ru Group)
Author-email: dev@maps.me
License: UNKNOWN
Platform: UNKNOWN
Classifier: Programming Language :: Python :: 3
Classifier: License :: OSI Approved :: Apache Software License
Requires-Python: >=3.6
Requires-Dist: omim-mwm (==10.3.0rc2)
